git_cai_cli/__init__.py
git_cai_cli/_version.py
git_cai_cli/cli.py
git_cai_cli/core/__init__.py
git_cai_cli/core/config.py
git_cai_cli/core/gitutils.py
git_cai_cli/core/languages.py
git_cai_cli/core/llm.py
git_cai_cli/core/options.py
git_cai_cli/core/squash.py
git_cai_cli/core/validate.py
git_cai_cli-0.6.1.dist-info/licenses/LICENSE
git_cai_cli-0.6.1.dist-info/METADATA
git_cai_cli-0.6.1.dist-info/WHEEL
git_cai_cli-0.6.1.dist-info/entry_points.txt
git_cai_cli-0.6.1.dist-info/top_level.txt
git_cai_cli-0.6.1.dist-info/RECORD
