Metadata-Version: 2.4
Name: git-cai-cli
Version: 0.6.1
Summary: Use LLM to create git commit messages
Author-email: Thorsten Foltz <thorsten.foltz@live.com>
License: MIT
Project-URL: Homepage, https://github.com/thorstenfoltz/cai
Project-URL: Issues, https://github.com/thorstenfoltz/cai/issues
Keywords: Git,LLM,Commit,AI,GenAI
Classifier: Development Status :: 4 - Beta
Classifier: Environment :: Console
Classifier: Intended Audience :: Developers
Classifier: Programming Language :: Python :: 3
Classifier: Programming Language :: Python :: 3.10
Classifier: Programming Language :: Python :: 3.11
Classifier: Programming Language :: Python :: 3.12
Classifier: Programming Language :: Python :: 3.13
Classifier: Programming Language :: Python :: 3.14
Classifier: Operating System :: OS Independent
Classifier: Topic :: Software Development :: Version Control
Requires-Python: >=3.10
License-File: LICENSE
Requires-Dist: pyyaml>=6.0
Requires-Dist: openai>=1.0
Requires-Dist: google-genai>=1.39
Requires-Dist: typer>=0.19.2
Requires-Dist: requests>=2.32.5
Requires-Dist: anthropic>=0.75.0
Requires-Dist: groq>=0.37.0
Dynamic: license-file
